{"filename": "0260_HDR.hdr", "path": "C:/Users/remis/sources/DD/images/HDR", "description": null, "exif": {"Image Width": 5997, "Image Height": 3373, "Dynamic Range (stops)": 8.6126732668235, "Exposure Time": null, "F Number": null, "ISO": null, "Bits Per Sample": 32, "Color Space": "scRGB", "Camera": null, "Software": null, "Lens": null, "Focal Length": null}, "processpipe": [{"exposure": {"EV": -1.5}}, {"contrast": {"contrast": 0}}, {"tonecurve": {"start": [0, 0], "shadows": [10, 19.0], "blacks": [30, 39.0], "mediums": [50, 59.0], "whites": [70, 76.0], "highlights": [90, 93.0], "end": [100, 100]}}, {"lightnessmask": {"shadows": false, "blacks": false, "mediums": false, "whites": false, "highlights": false}}, {"saturation": {"saturation": 6, "method": "gamma"}}, {"colorEditor0": {"selection": {"lightness": [0, 100], "chroma": [0, 100], "hue": [0, 360]}, "edit": {"exposure": 0.0, "contrast": 0.0, "saturation": 0.0}, "mask": false}}, {"colorEditor1": {"selection": {"lightness": [0, 100], "chroma": [0, 100], "hue": [0, 360]}, "edit": {"exposure": 0.0, "contrast": 0.0, "saturation": 0.0}, "mask": false}}, {"colorEditor2": {"selection": {"lightness": [0, 100], "chroma": [0, 100], "hue": [0, 360]}, "edit": {"exposure": 0.0, "contrast": 0.0, "saturation": 0.0}, "mask": false}}, {"colorEditor3": {"selection": {"lightness": [0, 100], "chroma": [0, 100], "hue": [0, 360]}, "edit": {"exposure": 0.0, "contrast": 0.0, "saturation": 0.0}, "mask": false}}, {"colorEditor4": {"selection": {"lightness": [0, 100], "chroma": [0, 100], "hue": [0, 360]}, "edit": {"exposure": 0.0, "contrast": 0.0, "saturation": 0.0}, "mask": false}}, {"geometry": {"ratio": [16, 9], "up": 0, "rotation": 0.0}}], "display": null, "uHDR TAGS": [{"scoring": {"*     (1)": null, "**    (2)": null, "***   (3)": null, "****  (4)": null, "***** (5)": null}}, {"scene": {"landscape": null, "seaside": null, "cityscape": null, "architecture": null, "interiors": null, "still life": null, "portrait": null, "event": null}}, {"light mood": {"night": null, "dark": null, "soft (indoor)": null, "soft (outdoor)": null, "bright": null, "very bright": null}}]}